grizzled/__init__.py
grizzled/decorators.py
grizzled/log.py
grizzled/misc.py
grizzled/os.py
grizzled/proxy.py
grizzled/collections/__init__.py
grizzled/collections/dict.py
grizzled/file/__init__.py
grizzled/file/includer.py
grizzled/io/__init__.py
grizzled/io/filelock.py
grizzled/text/__init__.py
test/__init__.py
test/collections/__init__.py
test/collections/test_lru_dict.py
test/file/__init__.py
test/file/test_eglob.py
test/file/test_includer.py
test/file/test_misc.py
test/io/__init__.py
test/io/test_pushback.py
test/misc/__init__.py
test/misc/test_bitcount.py
test/misc/test_read_only.py
test/text/__init__.py
test/text/test_str2bool.py
grizzled_python-2.2.0.dist-info/LICENSE.md
grizzled_python-2.2.0.dist-info/METADATA
grizzled_python-2.2.0.dist-info/WHEEL
grizzled_python-2.2.0.dist-info/top_level.txt
grizzled_python-2.2.0.dist-info/RECORD
